Workbook
Name Slicer_Education_Level: #N/A
Name Slicer_Education_Level1: #N/A
Name Slicer_Gender: #N/A
Name Slicer_Gender1: #N/A
Name Slicer_Region: #N/A
Name Slicer_Region1: #N/A
Name Slicer_Risk_Level: #N/A
Name Slicer_Risk_Level1: #N/A

Sheet Raw_Data
A1: Customer_ID | B1: Age | C1: Gender | D1: Education_Level | E1: Region | F1: Monthly_Income | G1: Account_Balance | H1: Credit_Score | I1: Days_in_Arrears_12M | J1: Requested_Loan_Amount
A2: 1 | B2: 56 | C2: Male | D2: Secondary School | E2: North | F2: 3390.29 | G2: 7044.24 | H2: 630 | I2: 5 | J2: 8575.03
A3: 2 | B3: 69 | C3: Female | D3: Primary School | E3: South | F3: 1294.19 | G3: 1634.55 | H3: 548 | I3: 8
A4: 3 | B4: 46 | C4: Male | D4: Technical | E4: Central | G4: 2532.94 | H4: 507 | I4: 8 | J4: 4227.19
A5: 4 | B5: 32 | C5: Female | D5: University | E5: North | F5: 2951.14 | G5: 6405.47 | H5: 591 | I5: 4 | J5: 9040.18
A6: 5 | B6: 60 | C6: Female | D6: Postgraduate | E6: South | F6: 3701.95 | G6: 7720.67 | H6: 641 | I6: 8 | J6: 12337.47
A7: 6 | B7: 25 | C7: Male | D7: Secondary School | E7: Central | F7: 1419.09 | G7: 1028.84 | H7: 461 | I7: 7 | J7: 6198.48
A8: 7 | B8: 38 | C8: Female | D8: Technical | E8: Central | F8: 2471.13 | G8: 5243.97 | H8: 551 | I8: 11 | J8: 4004.28
A9: 8 | B9: 56 | C9: Male | D9: Technical | E9: Central | F9: 2542.31 | G9: 3504.86 | H9: 590 | I9: 5 | J9: 10339.74
A10: 9 | B10: 75 | C10: Male | D10: Secondary School | E10: North | F10: 1731.57 | G10: 3968.05 | H10: 566 | I10: 6 | J10: 4292.98
A11: 10 | B11: 36 | C11: Female | D11: Technical | E11: North | F11: 5555.99 | G11: 10830.6 | H11: 765 | I11: 7 | J11: 19495.39
A12: 11 | B12: 40 | C12: Female | D12: Secondary School | E12: Central | F12: 3717.61 | H12: 712 | I12: 6 | J12: 11371.33
A13: 12 | B13: 28 | C13: Male | D13: Postgraduate | E13: Central | F13: 4347.55 | G13: 9188.65 | H13: 703 | I13: 6 | J13: 15183.55
A14: 13 | B14: 28 | C14: Female | D14: Technical | E14: West | F14: 3110.16 | G14: 5786.8 | H14: 729 | I14: 3 | J14: 10295.88
A15: 14 | B15: 41 | C15: Male | D15: University | E15: North | F15: 1865.74 | G15: 3160.1 | H15: 577 | I15: 11 | J15: 5540.82
A16: 15 | B16: 70 | C16: Male | D16: Secondary School | E16: West | F16: 1692.84 | G16: 3030.23 | H16: 607 | I16: 6 | J16: 5573.22
A17: 16 | B17: 53 | C17: Female | D17: Primary School | E17: Central | G17: 3134.45 | H17: 561 | I17: 4 | J17: 3779.12
A18: 17 | B18: 57 | C18: Male | D18: Secondary School | E18: Central | F18: 3052.76 | G18: 5287.29 | H18: 676 | I18: 10 | J18: 9672.18
A19: 18 | B19: 41 | C19: Male | D19: University | E19: Central | F19: 1586.7 | G19: 2706.68 | I19: 7 | J19: 3183.71
A20: 19 | B20: 20 | C20: Female | D20: University | E20: Central | F20: 1802.05 | G20: 4145.52 | I20: 9 | J20: 4371.58
A21: 20 | B21: 39 | C21: Female | D21: Secondary School | E21: South | F21: 1630.59 | G21: 1899.43 | H21: 549 | I21: 7 | J21: 7711.76
A22: 21 | B22: 70 | C22: Male | D22: University | E22: Central | F22: 5309.31 | G22: 10420.72 | I22: 7 | J22: 19642.27
A23: 22 | B23: 19 | C23: Male | D23: Secondary School | E23: South | F23: 1564.57 | G23: 2809.47 | I23: 8 | J23: 2630.01
A24: 23 | B24: 41 | C24: Female | D24: Secondary School | E24: Central | G24: 3598.92 | H24: 587 | I24: 4 | J24: 8110.74
A25: 24 | B25: 61 | C25: Female | D25: University | E25: South | F25: 2445.79 | G25: 4878.02 | I25: 10 | J25: 8389.16
A26: 25 | B26: 47 | C26: Female | D26: University | E26: South | F26: 3552.84 | G26: 5152.55 | H26: 690 | I26: 1 | J26: 12538.55
A27: 26 | B27: 55 | C27: Male | D27: Secondary School | F27: 994.37 | H27: 538 | I27: 10 | J27: 2964.31
A28: 27 | B28: 19 | C28: Male | D28: Secondary School | E28: East | F28: 1076.31 | G28: 3633.56 | H28: 540 | I28: 10 | J28: 3064.21
A29: 28 | B29: 38 | C29: Male | D29: Secondary School | E29: East | F29: 1402.57 | G29: 2166.02 | H29: 539 | I29: 5 | J29: 1161.27
A30: 29 | B30: 50 | C30: Female | D30: Secondary School | E30: West | F30: 937.86 | G30: 1388.55 | H30: 441 | I30: 7 | J30: 1462.95
A31: 30 | B31: 29 | C31: Female | D31: University | E31: North | F31: 1402.51 | G31: 3153.68 | H31: 576 | I31: 6
A32: 31 | B32: 75 | C32: Female | D32: Technical | E32: East | F32: 1650.35 | G32: 3478.78 | H32: 538 | I32: 8 | J32: 4572.75
A33: 32 | B33: 39 | C33: Female | D33: Primary School | E33: West | F33: 636.55 | G33: 1654.28 | I33: 9 | J33: 2599.14
A34: 33 | B34: 61 | C34: Male | D34: Secondary School | E34: South | F34: 1512.25 | G34: 2358.15 | H34: 621 | J34: 3381.26
A35: 34 | B35: 42 | C35: Male | D35: Postgraduate | E35: South | F35: 3839.79 | H35: 662 | I35: 11 | J35: 14169.42
A36: 35 | B36: 66 | C36: Male | D36: University | E36: West | F36: 1764.27 | G36: 2720.24 | H36: 590 | I36: 5
A37: 36 | B37: 44 | C37: Male | D37: University | E37: West | F37: 2102.16 | G37: 4157.24 | H37: 634 | I37: 6 | J37: 5723.01
A38: 37 | B38: 59 | C38: Male | D38: Primary School | E38: South | F38: 1068.65 | G38: 1819.64 | H38: 514 | I38: 10 | J38: 2692
A39: 38 | B39: 45 | C39: Male | D39: University | E39: Central | F39: 4938.18 | G39: 9499.79 | H39: 708 | I39: 7 | J39: 16223.32
A40: 39 | B40: 33 | C40: Female | D40: Secondary School | E40: East | F40: 1584.77 | G40: 3575.98 | H40: 619 | I40: 5 | J40: 5423.88
A41: 40 | B41: 32 | C41: Female | D41: Technical | E41: North | F41: 4875.56 | G41: 9124.41 | H41: 660 | I41: 4 | J41: 16661.07
A42: 41 | B42: 64 | C42: Male | D42: Postgraduate | E42: Central | F42: 2861.69 | G42: 4535.75 | H42: 650 | I42: 5 | J42: 10194.82
A43: 42 | B43: 68 | C43: Female | D43: Primary School | E43: West | F43: 1047.38 | G43: 679.05 | H43: 526 | I43: 9 | J43: 924.23
A44: 43 | B44: 61 | C44: Male | D44: Secondary School | E44: East | F44: 2612.94 | G44: 3797.23 | H44: 544 | I44: 9 | J44: 6958.89
A45: 44 | B45: 72 | C45: Female | D45: Primary School | E45: West | F45: 408.99 | G45: 0 | H45: 383 | I45: 5 | J45: 1048
A46: 45 | B46: 69 | C46: Female | D46: Secondary School | E46: South | F46: 2246.25 | G46: 6436.58 | H46: 563 | I46: 2 | J46: 7763.49
A47: 46 | B47: 74 | C47: Female | D47: Secondary School | E47: Central | F47: 1530.52 | G47: 3282.38 | H47: 598 | I47: 13 | J47: 4030.34
A48: 47 | B48: 20 | C48: Male | D48: University | F48: 2417.51 | G48: 4532.71 | H48: 613 | I48: 8 | J48: 8556.54
A49: 48 | B49: 54 | C49: Male | D49: Secondary School | E49: Central | G49: 1935.72 | H49: 530 | I49: 7 | J49: 500
A50: 49 | B50: 68 | C50: Male | D50: Technical | E50: East | F50: 2469.33 | G50: 5194.83 | H50: 617 | I50: 8 | J50: 8013.34
A51: 50 | B51: 24 | C51: Female | D51: University | E51: South | F51: 1009.12 | G51: 1662.39 | I51: 3 | J51: 4092.29
A52: 51 | B52: 38 | C52: Female | D52: Postgraduate | E52: Central | G52: 4493.54 | H52: 605 | I52: 8 | J52: 7832.14
A53: 52 | B53: 26 | C53: Female | D53: Secondary School | E53: North | F53: 3510.55 | G53: 6798.24 | H53: 671 | I53: 4 | J53: 13867.22
A54: 53 | B54: 56 | C54: Male | D54: Secondary School | F54: 1587.56 | G54: 3190.98 | H54: 529 | I54: 9 | J54: 4122.31
A55: 54 | B55: 35 | C55: Female | D55: Primary School | E55: South | G55: 1306.68 | H55: 487 | I55: 13 | J55: 2899.01
A56: 55 | B56: 21 | C56: Female | D56: Primary School | E56: North | F56: 1183.61 | G56: 1318.83 | H56: 554 | I56: 4
A57: 56 | B57: 42 | C57: Male | D57: Technical | E57: Central | F57: 2521.18 | G57: 4586.02 | H57: 556 | I57: 8 | J57: 10024.75
A58: 57 | B58: 31 | C58: Male | D58: Primary School | E58: South | F58: 1227.1 | G58: 3077.88 | H58: 499 | I58: 7 | J58: 3944.34
A59: 58 | B59: 67 | C59: Female | D59: Secondary School | E59: East | F59: 1497.18 | G59: 3298.18 | H59: 518 | I59: 9 | J59: 2781.14
A60: 59 | B60: 75 | C60: Male | D60: Primary School | E60: North | F60: 980.59 | G60: 2019.39 | H60: 512 | I60: 9 | J60: 1983.63
A61: 60 | B61: 26 | C61: Female | D61: Technical | E61: South | F61: 986.91 | G61: 2428.63 | H61: 495 | I61: 4
A62: 61 | B62: 43 | C62: Female | D62: Secondary School | E62: North | F62: 648.18 | G62: 208.7 | H62: 471 | I62: 10 | J62: 2584.34
A63: 62 | B63: 70 | C63: Female | D63: Primary School | E63: North | F63: 871.69 | G63: 1440.93 | H63: 461 | I63: 10 | J63: 855.35
A64: 63 | B64: 19 | C64: Female | D64: Secondary School | E64: North | F64: 2587.54 | G64: 4624.81 | H64: 614 | I64: 5 | J64: 6973.65
A65: 64 | B65: 37 | C65: Female | D65: Technical | E65: South | F65: 1473.22 | G65: 1794.93 | H65: 529 | I65: 10 | J65: 2691.12
A66: 65 | B66: 45 | C66: Female | D66: Technical | E66: North | F66: 1683.88 | H66: 511 | I66: 8 | J66: 5513.92
A67: 66 | B67: 64 | C67: Male | D67: Secondary School | F67: 789.35 | G67: 1967.05 | H67: 428 | I67: 4 | J67: 1688.94
A68: 67 | B68: 24 | C68: Male | D68: University | E68: North | F68: 2323.1 | G68: 4312.88 | H68: 526 | I68: 8 | J68: 5380.59
A69: 68 | B69: 61 | C69: Male | D69: Primary School | E69: West | G69: 2030.9 | H69: 557 | I69: 5 | J69: 5144.37
A70: 69 | B70: 25 | C70: Female | D70: Primary School | E70: West | G70: 1322.17 | I70: 15 | J70: 758.44
A71: 70 | B71: 64 | C71: Male | D71: Primary School | E71: North | F71: 958.91 | G71: 1258.32 | I71: 5 | J71: 2147.99
A72: 71 | B72: 52 | C72: Male | D72: Technical | E72: Central | F72: 1414.64 | G72: 1456.42 | H72: 607 | I72: 12 | J72: 6045.65
A73: 72 | B73: 31 | C73: Male | D73: Technical | E73: West | F73: 1579.39 | G73: 2694.73 | H73: 532 | I73: 7 | J73: 5051.82
A74: 73 | B74: 34 | C74: Female | D74: Primary School | E74: North | F74: 1165.25 | G74: 1620.2 | H74: 548 | I74: 5 | J74: 4145.18
A75: 74 | B75: 53 | C75: Female | D75: Technical | E75: North | F75: 665.66 | G75: 555.91 | H75: 435 | I75: 8 | J75: 3166.54
A76: 75 | B76: 67 | C76: Female | D76: Secondary School | E76: North | F76: 739.23 | G76: 1374.95 | H76: 479 | I76: 7 | J76: 1127.4
A77: 76 | B77: 57 | C77: Male | D77: Postgraduate | E77: West | F77: 2681.53 | G77: 4530.11 | H77: 623 | I77: 9 | J77: 8434.83
A78: 77 | B78: 21 | C78: Female | D78: Technical | E78: East | F78: 2614.8 | G78: 3580.78 | H78: 570 | I78: 8
A79: 78 | B79: 19 | C79: Female | D79: Technical | E79: North | F79: 909.09 | G79: 1193.08 | H79: 553 | I79: 3 | J79: 2709.8
A80: 79 | B80: 23 | C80: Male | D80: Technical | E80: North | F80: 2251.31 | G80: 3946.41 | H80: 639 | I80: 8 | J80: 8046.82
A81: 80 | B81: 71 | C81: Female | D81: Postgraduate | E81: West | F81: 7357.55 | G81: 12365.82 | H81: 742 | I81: 6 | J81: 26090.97
A82: 81 | B82: 59 | C82: Male | D82: Postgraduate | F82: 3027.09 | G82: 5729.63 | H82: 613 | I82: 8 | J82: 9307.04
A83: 82 | B83: 21 | C83: Female | D83: Technical | E83: South | F83: 1410.96 | G83: 2600.24 | J83: 4546.8
A84: 83 | B84: 71 | C84: Male | D84: Secondary School | E84: Central | F84: 2021.27 | G84: 2938.48 | H84: 587 | I84: 7 | J84: 4256.51
A85: 84 | B85: 46 | C85: Male | D85: Secondary School | E85: East | F85: 1588.97 | G85: 3483.81 | H85: 521 | I85: 8 | J85: 3263.59
A86: 85 | B86: 35 | C86: Female | D86: Secondary School | E86: North | F86: 1118.67 | G86: 3123.53 | H86: 508 | I86: 8 | J86: 2092.61
A87: 86 | B87: 43 | C87: Male | D87: Technical | E87: East | F87: 2040.34 | G87: 3615.94 | H87: 643 | I87: 10 | J87: 5898.8
A88: 87 | B88: 61 | C88: Male | D88: Secondary School | E88: Central | F88: 1143.75 | G88: 1889.71 | I88: 5 | J88: 2216.63
A89: 88 | B89: 51 | C89: Female | D89: University | E89: North | F89: 4540.2 | G89: 7917.29 | H89: 750 | I89: 8 | J89: 17103.39
A90: 89 | B90: 27 | C90: Male | D90: Secondary School | E90: Central | F90: 1322.48 | G90: 1960.43 | H90: 484 | I90: 12 | J90: 1902.94
A91: 90 | B91: 53 | C91: Female | D91: University | E91: East | F91: 2968.88 | G91: 4595.14 | H91: 687 | I91: 2 | J91: 7846.56
A92: 91 | B92: 31 | C92: Male | D92: Secondary School | E92: Central | F92: 3105.95 | H92: 689 | I92: 6 | J92: 11132.15
A93: 92 | B93: 48 | C93: Female | D93: Technical | E93: North | F93: 1680.22 | G93: 2415.02 | H93: 609 | I93: 9 | J93: 4689.44
A94: 93 | B94: 65 | C94: Female | D94: Secondary School | E94: South | F94: 1119.03 | G94: 0 | I94: 8 | J94: 3976.62
A95: 94 | B95: 32 | C95: Female | D95: Technical | E95: South | F95: 1364.76 | G95: 4081.73 | H95: 531 | I95: 6 | J95: 2336.91
A96: 95 | B96: 25 | C96: Female | D96: Secondary School | E96: East | F96: 1448.43 | G96: 3965.05 | I96: 6 | J96: 4294.85
A97: 96 | B97: 31 | C97: Female | D97: Secondary School | E97: Central | F97: 1376.74 | G97: 2567.39 | H97: 541 | I97: 8 | J97: 5396.64
A98: 97 | B98: 40 | C98: Female | D98: University | E98: North | F98: 2207.73 | G98: 2934.19 | H98: 607 | I98: 11 | J98: 4979.27
A99: 98 | B99: 74 | C99: Female | D99: Primary School | E99: South | F99: 1494.19 | G99: 4528.82 | H99: 520 | I99: 11 | J99: 5999.63
A100: 99 | B100: 57 | C100: Female | D100: Secondary School | E100: Central | F100: 1632.58 | G100: 3354.27 | H100: 529 | I100: 6 | J100: 2366.09
...

Sheet Data_Dictionary
A3: Column Name | B3: Data Type | C3: Description | D3: Business Meaning
A4: Customer_ID | B4: Identifier | C4: Unique customer identifier | D4: Identifies each customer
A5: Age | B5: Numeric | C5: Customer age | D5: Used for demographic analysis
A6: Gender | B6: Categorical | C6: Customer gender | D6: Used to analyze customer demographics
A7: Education_Level | B7: Categorical | C7: Customer's education level | D7: Helps analyze customer profile
A8: Region | B8: Categorical | C8: Customer geographical region | D8: Used for regional analysis
A9: Monthly_Income | B9: Numeric | C9: Customer monthly income | D9: Indicates customer's earning capacity
A10: Account_Balance | B10: Numeric | C10: Customer account balance | D10: Indicates customer's available account funds
A11: Credit_Score | B11: Numeric | C11: Customer credit score | D11: Indicates creditworthiness
A12: Days_in_Arrears_12M | B12: Numeric | C12: Days overdue during previous 12 months | D12: Indicates potential repayment risk
A13: Requested_Loan_Amount | B13: Numeric | C13: Loan amount requested by customer | D13: Indicates loan demand

Sheet Data_Quality_Audit
A3: Data Quality Metric | B3: Result
A4: Total Rows | B4: 1000
A5: Total Columns | B5: 10
A6: Duplicate Rows | B6: =COUNTA(A2:A10001)-SUMPRODUCT((A2:A10001<>"")/COUNTIF(A2:A10001,A2:A10001&"")) -> 5
A7: Missing Customer IDs | B7: =COUNTBLANK(Raw_Data!A2:A10001) -> 0
A8: Missing Age | B8: =COUNTBLANK(Raw_Data!B2:B10001) -> 0
A9: Missing Gender | B9: =COUNTBLANK(Raw_Data!C2:C10001) -> 0
A10: Missing Education Level | B10: =COUNTBLANK(Raw_Data!D2:D10001) -> 0
A11: Missing Region | B11: =COUNTBLANK(Raw_Data!E2:E10001) -> 303
A12: Missing Monthly Income | B12: =COUNTBLANK(Raw_Data!F2:F10001) -> 1088
A13: Missing Account Balance | B13: =COUNTBLANK(Raw_Data!G2:G10001) -> 565
A14: Missing Credit Score | B14: =COUNTBLANK(Raw_Data!H2:H10001) -> 1167
A15: Missing Days in Arrears | B15: =COUNTBLANK(Raw_Data!I1:I10001) -> 349
A16: Missing Requested Loan Amount | B16: =COUNTBLANK(Raw_Data!J2:J10001) -> 719
A18: Age Validation
A19: Validity Check | B19: Result
A20: Minimum Age | B20: =MIN(Raw_Data!B2:B10001) -> 18
A21: Maximum Age | B21: =MAX(Raw_Data!B2:B10001) -> 75
A22: Ages below 18 | B22: =COUNTIF(Raw_Data!B2:B10001,"<18") -> 0
A23: Ages above 100 | B23: =COUNTIF(Raw_Data!B2:B10001,">100") -> 0
A25: Monthly Income Validation
A26: Validity Check | B26: Result
A27: Minimum Monthly Income | B27: =MIN(Raw_Data!F2:F10001) -> 282.14
A28: Maximum Monthly Income | B28: =MAX(Raw_Data!F2:F10001) -> 13453.9
A29: Zero Income | B29: =COUNTIF(Raw_Data!F2:F10001,0) -> 0
A30: Negative Income | B30: =COUNTIF(Raw_Data!F2:F10001,"<0") -> 0
A32: Account Balance Validation
A33: Validity Check | B33: Result
A34: Minimum Account Balance | B34: =MIN(Raw_Data!G2:G10001) -> 0
A35: Maximum Account Balance | B35: =MAX(Raw_Data!G2:G10001) -> 24859.21
A36: Negative Balances | B36: =COUNTIF(Raw_Data!G2:G10001,"<0") -> 0
A38: Credit Score Validation
A39: Validity Check | B39: Result
A40: Minimum Credit Score | B40: =MIN(Raw_Data!H1:H2) -> 630
A41: Maximum Credit Score | B41: =MAX(Raw_Data!H2:H10001) -> 826
A42: Credit Score below 0 | B42: =COUNTIF(Raw_Data!H2:H10001,"<0") -> 0
A43: Credit Score above 1000 | B43: =COUNTIF(Raw_Data!H2:H10001,">1000") -> 0
A45: Days in Arrears
A46: Validity Check | B46: Result
A47: Minimum Days in Arrears | B47: =MIN(Raw_Data!I2:I10001) -> 0
A48: Maximum Days in Arrears | B48: =MAX(Raw_Data!I1:I2) -> 5
A49: Negative Arrears | B49: =COUNTIF(Raw_Data!I1:I2,"<0") -> 0
A51: Requested Loan Amount
A52: Validity Check | B52: Result
A53: Minimum Loan Amount | B53: =MIN(Raw_Data!J2:J10001) -> 500
A54: Maximum Loan Amount | B54: =MAX(Raw_Data!J2:J10001) -> 49577.93
A55: Zero Loan Amount | B55: =COUNTIF(Raw_Data!J2:J10001,0) -> 0
A56: Negative Loan Amount | B56: =COUNTIF(Raw_Data!J2:J10001,"<0") -> 0

Sheet cleaning_log
A2: Issue | B2: Column | C2: Count | D2: Action | E2: Reason
A3: Missing values | B3: Region | C3: 303 | D3: Replace with "Unknown" | E3: Categorical variable; avoids inventing a region
A4: Missing values | B4: Monthly Income | C4: 1088 | D4: Replace with Median | E4: Numeric variable; median is less affected by outliers
A5: Missing values | B5: Account Balance | C5: 565 | D5: Replace with Median | E5: Numeric variable; median is robust to outliers
A6: Missing values | B6: Credit Score | C6: 1167 | D6: Replace with Median | E6: Risk variable; preserves records without assuming zero
A7: Missing values | B7: Days in Arrears | C7: 349 | D7: Replace with Median | E7: Risk variable; preserves records
A8: Missing values | B8: Requested Loan Amount | C8: 719 | D8: Replace with Median | E8: Numeric variable; median reduces outlier influence

Sheet Descriptive_Statistics
A3: Statistic | B3: Age | C3: Monthly Income | D3: Account Balance | E3: Credit Score | F3: Days in Arrears | G3: Requested Loan Amount
A4: Count | B4: =COUNT(Table1[Age]) -> 10000 | C4: =COUNT(Raw_Data!F2:F10001) -> 8912 | D4: =COUNT(Raw_Data!G2:G10001) -> 9435 | E4: =COUNT(Raw_Data!H2:H10001) -> 8833 | F4: =COUNT(Raw_Data!I2:I10001) -> 9651 | G4: =COUNT(Raw_Data!J2:J10001) -> 9281
A5: Average | B5: =AVERAGE(Table1[Age]) -> 46.6835 | C5: =AVERAGE(Raw_Data!F2:F10001) -> 2059.4137 | D5: =AVERAGE(Raw_Data!G2:G10001) -> 3656.1023 | E5: =AVERAGE(Raw_Data!H2:H10001) -> 577.53787 | F5: =AVERAGE(Raw_Data!I2:I10001) -> 7.2485753 | G5: =AVERAGE(Raw_Data!J2:J10001) -> 6346.8111
A6: Median | B6: =MEDIAN(Table1[Age]) -> 46 | C6: =MEDIAN(Raw_Data!F2:F10001) -> 1772.225 | D6: =MEDIAN(Raw_Data!G2:G10001) -> 3237.28 | E6: =MEDIAN(Raw_Data!H2:H10001) -> 576 | F6: =MEDIAN(Raw_Data!I2:I10001) -> 7 | G6: =MEDIAN(Raw_Data!J2:J10001) -> 5332.54
A7: Minimum | B7: =MIN(Table1[Age]) -> 18 | C7: =MIN(Raw_Data!F2:F10001) -> 282.14 | D7: =MIN(Raw_Data!G2:G10001) -> 0 | E7: =MIN(Raw_Data!H2:H10001) -> 312 | F7: =MIN(Raw_Data!I2:I10001) -> 0 | G7: =MIN(Raw_Data!J2:J10001) -> 500
A8: Maximum | B8: =MAX(Table1[Age]) -> 75 | C8: =MAX(Raw_Data!F2:F10001) -> 13453.9 | D8: =MAX(Raw_Data!G2:G10001) -> 24859.21 | E8: =MAX(Raw_Data!H2:H10001) -> 826 | F8: =MAX(Raw_Data!I2:I10001) -> 20 | G8: =MAX(Raw_Data!J2:J10001) -> 49577.93
A9: Std. Deviation | B9: =_xlfn.STDEV.S(Table1[Age]) -> 16.717963 | C9: =_xlfn.STDEV.S(Raw_Data!F2:F10001) -> 1206.0328 | D9: =_xlfn.STDEV.S(Raw_Data!G2:G10001) -> 2275.4885 | E9: =_xlfn.STDEV.S(Raw_Data!H2:H10001) -> 78.085684 | F9: =_xlfn.STDEV.S(Raw_Data!I2:I10001) -> 2.76714 | G9: =_xlfn.STDEV.S(Raw_Data!J2:J10001) -> 4744.9733

Sheet Outlier_Analysis
A2: Variable | B2: Q1 | C2: Q3 | D2: IQR | E2: Lower Bound | F2: Upper Bound | G2: Outlier Count | H2: Outlier %
A3: Age | B3: =_xlfn.QUARTILE.INC(Table1[Age],1) -> 32 | C3: =_xlfn.QUARTILE.INC(Table1[Age],3) -> 61 | D3: =C3-B3 -> 29 | E3: =B3-(1.5*D3) -> -11.5 | F3: =C3+(1.5*D3) -> 104.5 | G3: =COUNTIF(Table1[Age],"<"&Outlier_Analysis!E3)+COUNTIF(Table1[Age],">"&Outlier_Analysis!F3) -> 0 | H3: =G3/COUNT(Table1[Age]) -> 0
A4: Monthly_Income | B4: =_xlfn.QUARTILE.INC(Raw_Data!F2:F10001,1) -> 1244.3075 | C4: =_xlfn.QUARTILE.INC(Raw_Data!F2:F10001,3) -> 2540.4 | D4: =C4-B4 -> 1296.0925 | E4: =B4-(1.5*D4) -> -699.83125 | F4: =C4+(1.5*D4) -> 4484.5388 | G4: =COUNTIF(Raw_Data!F2:F10001,"<"&E4)+COUNTIF(Raw_Data!F2:F10001,">"&F4) -> 400 | H4: =G4/COUNT(Raw_Data!F2:F10001) -> 0.044883303
A5: Account_Balance | B5: =_xlfn.QUARTILE.INC(Raw_Data!G2:G10001,1) -> 2126.87 | C5: =_xlfn.QUARTILE.INC(Raw_Data!G2:G10001,3) -> 4657.86 | D5: =C5-B5 -> 2530.99 | E5: =B5-(1.5*D5) -> -1669.615 | F5: =C5+(1.5*D5) -> 8454.345 | G5: =COUNTIF(Raw_Data!G2:G10001,"<"&Outlier_Analysis!E5)+COUNTIF(Raw_Data!G2:G10001,">"&Outlier_Analysis!F5) -> 360 | H5: =G5/COUNT(Raw_Data!G2:G10001) -> 0.038155803
A6: Credit_Score | B6: =_xlfn.QUARTILE.INC(Raw_Data!H2:H10001,1) -> 524 | C6: =_xlfn.QUARTILE.INC(Raw_Data!H2:H10001,3) -> 632 | D6: =C6-B6 -> 108 | E6: =B6-(1.5*D6) -> 362 | F6: =C6+(1.5*D6) -> 794 | G6: =COUNTIF(Raw_Data!H2:H10001,"<"&Outlier_Analysis!E6)+COUNTIF(Raw_Data!H2:H10001,">"&Outlier_Analysis!F6) -> 36 | H6: =G6/COUNT(Raw_Data!H2:H10001) -> 0.0040756255
A7: Days_in_ Arrears | B7: =_xlfn.QUARTILE.INC(Raw_Data!I1:I10001,1) -> 5 | C7: =_xlfn.QUARTILE.INC(Raw_Data!I1:I10001,3) -> 9 | D7: =C7-B7 -> 4 | E7: =B7-(1.5*D7) -> -1 | F7: =C7+(1.5*D7) -> 15 | G7: =COUNTIF(Raw_Data!I2:I10001,"<"&Outlier_Analysis!E7)+COUNTIF(Raw_Data!I2:I10001,">"&Outlier_Analysis!F7) -> 44 | H7: =G7/COUNT(Raw_Data!I2:I10001) -> 0.004559113
A8: Requested_ Loan _Amount | B8: =_xlfn.QUARTILE.INC(Raw_Data!J1:J10001,1) -> 3177.4 | C8: =_xlfn.QUARTILE.INC(Raw_Data!J1:J10001,3) -> 8196.84 | D8: =(C8-B8) -> 5019.44 | E8: =B8-(1.5*D8) -> -4351.76 | F8: =C8+(1.5*D8) -> 15726 | G8: =COUNTIF(Raw_Data!J2:J10001,"<"&Outlier_Analysis!E8)+COUNTIF(Raw_Data!J2:J10001,">"&Outlier_Analysis!F8) -> 430 | H8: =G8/COUNT(Raw_Data!J2:J10001) -> 0.046331214

Sheet Missing_Value_Treatment.
A2: Column | B2: Median Replacement Value
A3: Monthly Income | B3: =MEDIAN(Raw_Data!F2:F10001) -> 1772.225
A4: Account Balance | B4: =MEDIAN(Raw_Data!G2:G10001) -> 3237.28
A5: Credit Score | B5: =MEDIAN(Raw_Data!H2:H10001) -> 576
A6: Days in Arrears | B6: =MEDIAN(Raw_Data!I2:I10001) -> 7
A7: Requested Loan Amount | B7: =MEDIAN(Raw_Data!J2:J10001) -> 5332.54

Sheet Sheet3
A3: Row Labels | B3: Count of Customer_ID
A4: High Risk | B4: 267
A5: Low Risk | B5: 7762
A6: Moderate Risk | B6: 1971
A7: Grand Total | B7: 10000

Sheet Sheet1
A3: Row Labels | B3: Count of Customer_ID
A4: Female | B4: 4838
A5: Male | B5: 5162
A6: Grand Total | B6: 10000
A9: Row Labels | B9: Count of Customer_ID
A10: Postgraduate | B10: 617
A11: Primary School | B11: 1787
A12: Secondary School | B12: 3436
A13: Technical | B13: 1988
A14: University | B14: 2172
A15: Grand Total | B15: 10000

Sheet Cleaned_Data
A1: Customer_ID | B1: Age | C1: Gender | D1: Education_Level | E1: Region | F1: Monthly_Income | G1: Account_Balance | H1: Credit_Score | I1: Days_in_Arrears_12M | J1: Requested_Loan_Amount | K1: Risk_Level
A2: 1 | B2: 56 | C2: Male | D2: Secondary School | E2: North | F2: 3390.29 | G2: 7044.24 | H2: 630 | I2: 5 | J2: 8575.03 | K2: =IF(AND(H2<500,I2>10),"High Risk",IF(OR(H2<500,I2>10),"Moderate Risk","Low Risk")) -> Low Risk
A3: 2 | B3: 69 | C3: Female | D3: Primary School | E3: South | F3: 1294.19 | G3: 1634.55 | H3: 548 | I3: 8 | J3: 5332.54 | K3: =IF(AND(H3<500,I3>10),"High Risk",IF(OR(H3<500,I3>10),"Moderate Risk","Low Risk")) -> Low Risk
A4: 3 | B4: 46 | C4: Male | D4: Technical | E4: Central | F4: 1772.225 | G4: 2532.94 | H4: 507 | I4: 8 | J4: 4227.19 | K4: =IF(AND(H4<500,I4>10),"High Risk",IF(OR(H4<500,I4>10),"Moderate Risk","Low Risk")) -> Low Risk
A5: 4 | B5: 32 | C5: Female | D5: University | E5: North | F5: 2951.14 | G5: 6405.47 | H5: 591 | I5: 4 | J5: 9040.18 | K5: =IF(AND(H5<500,I5>10),"High Risk",IF(OR(H5<500,I5>10),"Moderate Risk","Low Risk")) -> Low Risk
A6: 5 | B6: 60 | C6: Female | D6: Postgraduate | E6: South | F6: 3701.95 | G6: 7720.67 | H6: 641 | I6: 8 | J6: 12337.47 | K6: =IF(AND(H6<500,I6>10),"High Risk",IF(OR(H6<500,I6>10),"Moderate Risk","Low Risk")) -> Low Risk
A7: 6 | B7: 25 | C7: Male | D7: Secondary School | E7: Central | F7: 1419.09 | G7: 1028.84 | H7: 461 | I7: 7 | J7: 6198.48 | K7: =IF(AND(H7<500,I7>10),"High Risk",IF(OR(H7<500,I7>10),"Moderate Risk","Low Risk")) -> Moderate Risk
A8: 7 | B8: 38 | C8: Female | D8: Technical | E8: Central | F8: 2471.13 | G8: 5243.97 | H8: 551 | I8: 11 | J8: 4004.28 | K8: =IF(AND(H8<500,I8>10),"High Risk",IF(OR(H8<500,I8>10),"Moderate Risk","Low Risk")) -> Moderate Risk
A9: 8 | B9: 56 | C9: Male | D9: Technical | E9: Central | F9: 2542.31 | G9: 3504.86 | H9: 590 | I9: 5 | J9: 10339.74 | K9: =IF(AND(H9<500,I9>10),"High Risk",IF(OR(H9<500,I9>10),"Moderate Risk","Low Risk")) -> Low Risk
A10: 9 | B10: 75 | C10: Male | D10: Secondary School | E10: North | F10: 1731.57 | G10: 3968.05 | H10: 566 | I10: 6 | J10: 4292.98 | K10: =IF(AND(H10<500,I10>10),"High Risk",IF(OR(H10<500,I10>10),"Moderate Risk","Low Risk")) -> Low Risk
A11: 10 | B11: 36 | C11: Female | D11: Technical | E11: North | F11: 5555.99 | G11: 10830.6 | H11: 765 | I11: 7 | J11: 19495.39 | K11: =IF(AND(H11<500,I11>10),"High Risk",IF(OR(H11<500,I11>10),"Moderate Risk","Low Risk")) -> Low Risk
A12: 11 | B12: 40 | C12: Female | D12: Secondary School | E12: Central | F12: 3717.61 | G12: 3237.28 | H12: 712 | I12: 6 | J12: 11371.33 | K12: =IF(AND(H12<500,I12>10),"High Risk",IF(OR(H12<500,I12>10),"Moderate Risk","Low Risk")) -> Low Risk
A13: 12 | B13: 28 | C13: Male | D13: Postgraduate | E13: Central | F13: 4347.55 | G13: 9188.65 | H13: 703 | I13: 6 | J13: 15183.55 | K13: =IF(AND(H13<500,I13>10),"High Risk",IF(OR(H13<500,I13>10),"Moderate Risk","Low Risk")) -> Low Risk
... A10001: 10000 | B10001: 50 | C10001: Male | D10001: Primary School | E10001: South | F10001: 1012.62 | G10001: 1312.12 | H10001: 576 | I10001: 9 | J10001: 1736.18 | K10001: =IF(AND(H10001<500,I10001>10),"High Risk",IF(OR(H10001<500,I10001>10),"Moderate Risk","Low Risk")) -> Low Risk

Sheet Business_Analysis
A2: Bank Customer Financial & Credit Risk Analysis
A3: KPI | B3: Value
A4: Total Customers | B4: =COUNTA(Cleaned_Data!A2:A10001) -> 10000
A5: Average Age | B5: =AVERAGE(Cleaned_Data!B2:B10001) -> 46.6835
A6: Average Monthly Income | B6: =AVERAGE(Cleaned_Data!F2:F10001) -> 2028.1676
A7: Average Account Balance | B7: =AVERAGE(Cleaned_Data!G2:G10001) -> 3632.4388
A8: Average Credit Score | B8: =AVERAGE(Cleaned_Data!H2:H10001) -> 577.3584
A9: Average Days in Arrears | B9: =AVERAGE(Cleaned_Data!I2:I10001) -> 7.2399
A10: Average Requested Loan Amount | B10: =AVERAGE(Cleaned_Data!J2:J10001) -> 6273.885
A11: Total Requested Loan Amount | B11: =SUM(Cleaned_Data!J2:J10001) -> 62738850

Sheet Pivot Analysis
A2: Customer Count by Gender | F2: Financial Profile by Gender
A3: Gender | B3: Customer Count | D3: Gender | E3: Avg Income | F3: Avg Balance | G3: Avg Credit Score | H3: Avg Days in Arrears | I3: Avg Loan Requested
A4: Female | B4: 4838 | D4: Female | E4: 2038.487 | F4: 3650.0238 | G4: 577.62795 | H4: 7.170525 | I4: 6293.5421
A5: Male | B5: 5162 | D5: Male | E5: 2018.4959 | F5: 3615.9575 | G5: 577.10577 | H5: 7.3049206 | I5: 6255.4618
A6: Grand Total | B6: 10000 | D6: Grand Total | E6: 2028.1676 | F6: 3632.4388 | G6: 577.3584 | H6: 7.2399 | I6: 6273.885
A8: Customer Count by Education Level | F8: Financial Profile by Education Level
A9: Educational Level | B9: Customer Count
A10: Postgraduate | B10: 617 | D10: Educational Level | E10: Avg Income | F10: Avg Balance | G10: Avg Credit Score | H10: Avg Days in Arrears | I10: Avg Loan Requested | K10: Educational Level | L10: Avg Income | M10: Avg Loan Requested
A11: Primary School | B11: 1787 | D11: Postgraduate | E11: 3529.1579 | F11: 6264.8127 | G11: 645.29173 | H11: 6.5429498 | I11: 11950.238 | K11: Postgraduate | L11: 3529.1579 | M11: 11950.238
A12: Secondary School | B12: 3436 | D12: Primary School | E12: 1425.9072 | F12: 2468.1755 | G12: 538.64801 | H12: 7.654169 | I12: 3968.2907 | K12: Primary School | L12: 1425.9072 | M12: 3968.2907
A13: Technical | B13: 1988 | D13: Secondary School | E13: 1685.669 | F13: 3038.9993 | G13: 558.69529 | H13: 7.4118161 | I13: 4978.7226 | K13: Secondary School | L13: 1685.669 | M13: 4978.7226
A14: University | B14: 2172 | D14: Technical | E14: 2010.6657 | F14: 3651.4713 | G14: 582.45724 | H14: 7.1509054 | I14: 6192.9826 | K14: Technical | L14: 2010.6657 | M14: 6192.9826
A15: Grand Total | B15: 10000 | D15: University | E15: 2655.1229 | F15: 4763.9237 | G15: 614.76657 | H15: 6.9065378 | I15: 8681.2513 | K15: University | L15: 2655.1229 | M15: 8681.2513
D16: Grand Total | E16: 2028.1676 | F16: 3632.4388 | G16: 577.3584 | H16: 7.2399 | I16: 6273.885
A17: Customer Count by Region
A18: Region | B18: Customer Count | F18: Financial Profile by Region
A19: West | B19: 1409 | D19: Region | E19: Avg Income | F19: Avg Balance | G19: Avg Credit Score | H19: Avg Days in Arrears | I19: Avg Loan Requested | K19: Region | L19: Avg Income | M19: Avg Balance
A20: Unknown | B20: 303 | D20: Central | E20: 2012.2728 | F20: 3636.0927 | G20: 576.36601 | H20: 7.3306001 | I20: 6229.0375 | K20: Central | L20: 2012.2728 | M20: 3636.0927
A21: South | B21: 1985 | D21: East | E21: 2050.551 | F21: 3686.0541 | G21: 577.20902 | H21: 7.2262774 | I21: 6297.6749 | K21: East | L21: 2050.551 | M21: 3686.0541
A22: North | B22: 2113 | D22: North | E22: 2035.5021 | F22: 3597.8631 | G22: 578.062 | H22: 7.2271652 | I22: 6269.0599 | K22: North | L22: 2035.5021 | M22: 3597.8631
A23: East | B23: 1507 | D23: South | E23: 2039.0121 | F23: 3647.4398 | G23: 579.76423 | H23: 7.1974811 | I23: 6360.412 | K23: South | L23: 2039.0121 | M23: 3647.4398
A24: Central | B24: 2683 | D24: West | E24: 1997.6212 | F24: 3594.0758 | G24: 574.16962 | H24: 7.17956 | I24: 6205.5781 | K24: West | L24: 1997.6212 | M24: 3594.0758
A25: Grand Total | B25: 10000 | D25: Unknown | E25: 2077.439 | F25: 3654.6609 | G25: 581.0495 | H25: 7.1518152 | I25: 6337.1145 | K25: Unknown | L25: 2077.439 | M25: 3654.6609
D26: Grand Total | E26: 2028.1676 | F26: 3632.4388 | G26: 577.3584 | H26: 7.2399 | I26: 6273.885 | K26: Grand Total | L26: 2028.1676 | M26: 3632.4388

Sheet Risk_Analysis
A1: Risk Indicator | B1: Customer Count | C1: Percentage
A2: Low Credit Score | B2: =COUNTIF(Cleaned_Data!H2:H10001,"<500") -> 1356 | C2: =B2/COUNTA(Cleaned_Data!A2:A10001) -> 0.1356
A3: High Days in Arrears | B3: =COUNTIF(Cleaned_Data!I2:I10001,">10") -> 1149 | C3: =B3/COUNTA(Cleaned_Data!A2:A10001) -> 0.1149
A4: Both Indicators | B4: =COUNTIFS(Cleaned_Data!H2:H10001,"<500",Cleaned_Data!I2:I10001,">10") -> 267 | C4: =B4/COUNTA(Cleaned_Data!A2:A10001) -> 0.0267
S6: Row Labels | T6: Sum of Customer Count | U6: Sum of Percentage
S7: High Risk | T7: 267 | U7: 0.0267
S8: Low Risk | T8: 7762 | U8: 0.7762
A9: Risk Segmentation table | S9: Moderate Risk | T9: 1971 | U9: 0.1971
A10: Risk Level | B10: Definition | C10: Customer Count | D10: Percentage | S10: Grand Total | T10: 10000 | U10: 1
A11: Low Risk | B11: No risk indicators | C11: =COUNTIFS(Cleaned_Data!H2:H10001,">=500",Cleaned_Data!I2:I10001,"<=10") -> 7762 | D11: =C11/COUNTA(Cleaned_Data!A2:A10001) -> 0.7762
A12: Moderate Risk | B12: One risk indicator | C12: =COUNTIFS(Cleaned_Data!H2:H10001,"<500",Cleaned_Data!I2:I10001,"<=10")+COUNTIFS(Cleaned_Data!H2:H10001,">=500",Cleaned_Data!I2:I10001,">10") -> 1971 | D12: =C12/COUNTA(Cleaned_Data!A2:A10001) -> 0.1971
A13: High Risk | B13: Both risk indicators | C13: =COUNTIFS(Cleaned_Data!H2:H10001,"<500",Cleaned_Data!I2:I10001,">10") -> 267 | D13: =C13/COUNTA(Cleaned_Data!A2:A10001) -> 0.0267
A14: Total | C14: =SUM(C11:C13) -> 10000 | D14: =SUM(D11:D13) -> 1
A18: Risk Analysis Insight
A20: 13.56% of customers show a low credit score based on the selected threshold.
A21: 11.49% show higher days in arrears.
A22: 2.67% exhibit both risk indicators simultaneously.
A23: Customers showing both indicators could be prioritized for further credit-risk review.

Sheet Dashboard
AL6: =Business_Analysis!B4 -> 10000
AL7: =Business_Analysis!B6 -> 2028.1676
AL8: =Business_Analysis!B7 -> 3632.4388
AL9: =Business_Analysis!B8 -> 577.3584
AL10: =Business_Analysis!B9 -> 7.2399
AL11: =Business_Analysis!B11 -> 62738850
AL12: =TEXT(AL11/1000000,"0.00")&"M" -> 62.74M
